pelican_albums/__init__.py
pelican_albums/content.py
pelican_albums/generator.py
pelican_albums/thumbnails.py
pelican_albums-0.6.1.dist-info/METADATA
pelican_albums-0.6.1.dist-info/WHEEL
pelican_albums-0.6.1.dist-info/top_level.txt
pelican_albums-0.6.1.dist-info/RECORD
