Metadata-Version: 2.1
Name: pelican-albums
Version: 0.6.1
Summary: Automatic photo album generation and thumbnailing for Pelican.
Home-page: https://github.com/iksteen/pelican-albums/
Author: Ingmar Steen
Author-email: iksteen@gmail.com
License: UNKNOWN
Download-URL: https://github.com/iksteen/pelican-albums/tarball/v0.6.1
Platform: UNKNOWN
Classifier: Environment :: Plugins
Classifier: Intended Audience :: Developers
Classifier: License :: OSI Approved :: MIT License
Classifier: Operating System :: OS Independent
Classifier: Programming Language :: Python
Classifier: Programming Language :: Python :: 2
Classifier: Programming Language :: Python :: 3
Classifier: Topic :: Internet :: WWW/HTTP
Classifier: Topic :: Software Development :: Libraries :: Python Modules
Requires-Dist: pillow
